mixology/__init__.py
mixology/_compat.py
mixology/assignment.py
mixology/constraint.py
mixology/failure.py
mixology/incompatibility.py
mixology/incompatibility_cause.py
mixology/package.py
mixology/package_source.py
mixology/partial_solution.py
mixology/range.py
mixology/result.py
mixology/set_relation.py
mixology/term.py
mixology/union.py
mixology/version_solver.py
mixology-0.2.0.dist-info/LICENSE
mixology-0.2.0.dist-info/WHEEL
mixology-0.2.0.dist-info/METADATA
mixology-0.2.0.dist-info/RECORD
