Metadata-Version: 2.1
Name: mixology
Version: 0.2.0
Summary: A generic dependency-resolution library written in pure Python
Home-page: https://github.com/sdispater/mixology
License: MIT
Keywords: dependency-resolution
Author: Sébastien Eustace
Author-email: sebastien@eustace.io
Requires-Python: >=2.7, !=3.0.*, !=3.1.*, !=3.2.*, !=3.3.*
Classifier: License :: OSI Approved :: MIT License
Classifier: Programming Language :: Python :: 2
Classifier: Programming Language :: Python :: 2.7
Classifier: Programming Language :: Python :: 3
Classifier: Programming Language :: Python :: 3.4
Classifier: Programming Language :: Python :: 3.5
Classifier: Programming Language :: Python :: 3.6
Classifier: Programming Language :: Python :: 3.7
Classifier: Programming Language :: Python :: 3.8
Classifier: Topic :: Software Development :: Libraries :: Python Modules
Requires-Dist: enum34 (>=1.1,<2.0); python_version >= "2.7" and python_version < "2.8"
Requires-Dist: typing (>=3.6,<4.0); python_version >= "2.7" and python_version < "2.8" or python_version >= "3.4" and python_version < "3.5"
Project-URL: Repository, https://github.com/sdispater/mixology
